ailca/__init__.py
ailca/temp.py
ailca/chem/__init__.py
ailca/chem/base.py
ailca/chem/crystal.py
ailca/chem/featvec.py
ailca/chem/formula.py
ailca/chem/image.py
ailca/chem/molecule.py
ailca/core/__init__.py
ailca/core/env.py
ailca/core/operation.py
ailca/core/sys.py
ailca/data/__init__.py
ailca/data/base.py
ailca/data/multimodal.py
ailca/data/util.py
ailca/ml/__init__.py
ailca/ml/base.py
ailca/ml/cnn.py
ailca/ml/fnn.py
ailca/ml/gnn.py
ailca/ml/hparams.py
ailca/ml/multimodal.py
ailca/ml/nn.py
ailca/ml/util.py
ailca-0.3.2.dist-info/LICENSE
ailca-0.3.2.dist-info/METADATA
ailca-0.3.2.dist-info/WHEEL
ailca-0.3.2.dist-info/top_level.txt
ailca-0.3.2.dist-info/RECORD
