Metadata-Version: 2.1
Name: ailca
Version: 0.3.2
Summary: Python package for chemical machine learning.
Author: Gyoung S. Na
Author-email: ngs0@krict.re.kr
Keywords: chemical science,materials science,artificial intelligence,machine learning
Requires-Python: >=3.9
License-File: LICENSE
